{
  "kind": "singleType",
  "collectionName": "globals",
  "info": {
    "singularName": "global",
    "pluralName": "globals",
    "displayName": "Global",
    "description": ""
  },
  "options": {
    "draftAndPublish": true
  },
  "attributes": {
    "Titulo": {
      "type": "string"
    },
    "Descripcion": {
      "type": "text"
    },
    "Navbar": {
      "type": "component",
      "repeatable": true,
      "component": "plano.navbar"
    },
    "Footer": {
      "displayName": "Footer",
      "type": "component",
      "repeatable": false,
      "component": "plano.footer"
    }
  }
}
